{
    "rank": {
        "Port": ":5200",
        "RedisUrl": "localhost:6379",
        "RedisPassword": "",
        "worldRankCount": 100,
        "countryRankCount": 100,
        "provinceRankCount": 100,
        "cityRankCount": 100,
        "Max": 1000   
    },
    "wx": {
        "appid": "wx43aafb42439d77c9",
        "appSecret": "f7f441021fad14b4fd4f37a131c855e4"
    },
    "bytedance": {
        "appid": "tt48373e8ad708d1e302",
        "appSecret": "082120aa73a6402f34d921bb6305f1b101498bd8"
    },
    "MongoDB": {
        "url": "localhost:27017",
        "SessionNum": 100,
        "DB": "sheep",
        "Collection": "user"
    },
    "DB": {
        "User":"root",
        "Password": "111111",
        "Host":"localhost:3306",
        "DB": "user",
        "MinAlive":100,
        "MaxAlive": 400,
        "MaxIdle": 5
    },
    "Urls": [
        "ws://192.168.50.240:3653"
    ],
    "SelfUrl":"ws://192.168.50.240",
    "QuestionTables": [
        "question-chuantonwenhua",
        "question-dili",
        "question-fagui",
        "question-jiankang",
        "question-keji",
        "question-lishi",
        "question-qita",
        "question-shenghuochangshi",
        "question-shengwu",
        "question-tiyv",
        "question-yingshi"
    ],
    "NewerTable": "question0",
    "SeverType":"gate"
}